pip_qt/__init__.py
pip_qt-0.0.9.dist-info/METADATA
pip_qt-0.0.9.dist-info/WHEEL
pip_qt-0.0.9.dist-info/top_level.txt
pip_qt-0.0.9.dist-info/RECORD
