Metadata-Version: 2.1
Name: pip-qt
Version: 0.0.9
Summary: pip manager
Author: Hannes
Project-URL: Source, https://github.com/hannesdelbeke/pip-qt
Keywords: pypi,pip,packages,package,installer
Classifier: Programming Language :: Python :: 3.7
Requires-Python: >=3.4
Requires-Dist: qtpy
Requires-Dist: py-pip
Requires-Dist: importlib-metadata ; python_version < "3.7"
